{
    "translations": {
        "de": {
            "Capacity": "Leistung",
            "Variance": "Varianz",
            "Interval": "Intervall",
            "seconds": "Sekunden",
            "Heater (Simulation)": "Heizstab (Simulation)",
            "Consumption": "Verbrauch",
            "Intensity": "Intensität",
            "https://www.symcon.de/en/service/documentation/module-reference/virtuelle-devices/heater-simulation/": "https://www.symcon.de/de/service/dokumentation/modulreferenz/virtuelle-geraete/heizstab-simulation/",
            "Virtual Heater": "Virtueller Heizstab"
        }
    }
}